MANIFEST.in
README.txt
setup.py
com/__init__.py
com/radware/__init__.py
com/radware/vdirect/__init__.py
com/radware/vdirect/dp/__init__.py
com/radware/vdirect/dp/demo.py
com/radware/vdirect/dp/dp6.py
com/radware/vdirect/dp/dp7.py
com/radware/vdirect/dp/dp8.py
com/radware/vdirect/dp/dp_client.py
com/radware/vdirect/dp/vdirect_configuration_templates/__dp_read_client__.vm
dp_client.egg-info/PKG-INFO
dp_client.egg-info/SOURCES.txt
dp_client.egg-info/dependency_links.txt
dp_client.egg-info/requires.txt
dp_client.egg-info/top_level.txt